setup.py
rgbkeyboards/__init__.py
rgbkeyboards/keyboard.py
rgbkeyboards/keyboards.py
rgbkeyboards/keygroups.py
rgbkeyboards/utilities.py
rgbkeyboards.egg-info/PKG-INFO
rgbkeyboards.egg-info/SOURCES.txt
rgbkeyboards.egg-info/dependency_links.txt
rgbkeyboards.egg-info/not-zip-safe
rgbkeyboards.egg-info/requires.txt
rgbkeyboards.egg-info/top_level.txt